umls_graph/__init__.py
umls_graph/dataset.py
umls_graph/umg_gui.py
umls_graph/umls_ambiglui.py
umls_graph/umls_ambigsui.py
umls_graph/umls_mrconso.py
umls_graph/umls_mrconso_concept.py
umls_graph/umls_mrconso_string.py
umls_graph/umls_mrconso_term.py
umls_graph/umls_mrdef.py
umls_graph/umls_mrrel.py
umls_graph/umls_mrsat.py
umls_graph/umls_mrsmap.py
umls_graph/umls_mrsty.py
umls_graph/umls_srdef.py
umls_graph/__pycache__/__init__.cpython-36.pyc
umls_graph/__pycache__/__init__.cpython-39.pyc
umls_graph/__pycache__/dataset.cpython-36.pyc
umls_graph/__pycache__/umls_ambiglui.cpython-36.pyc
umls_graph/__pycache__/umls_ambigsui.cpython-36.pyc
umls_graph/__pycache__/umls_mrconso.cpython-36.pyc
umls_graph/__pycache__/umls_mrconso_concept.cpython-36.pyc
umls_graph/__pycache__/umls_mrconso_string.cpython-36.pyc
umls_graph/__pycache__/umls_mrconso_term.cpython-36.pyc
umls_graph/__pycache__/umls_mrdef.cpython-36.pyc
umls_graph/__pycache__/umls_mrrel.cpython-36.pyc
umls_graph/__pycache__/umls_mrsat.cpython-36.pyc
umls_graph/__pycache__/umls_mrsmap.cpython-36.pyc
umls_graph/__pycache__/umls_mrsty.cpython-36.pyc
umls_graph/__pycache__/umls_srdef.cpython-36.pyc
umls_graph/gui/__init__.py
umls_graph/gui/main.py
umls_graph/gui/umls_fields.pickle
umls_graph/gui/umls_main.py
umls_graph/gui/umls_main.ui
umls_graph/gui/__pycache__/__init__.cpython-39.pyc
umls_graph/gui/__pycache__/main.cpython-39.pyc
umls_graph/gui/__pycache__/umls_main.cpython-39.pyc
umls_graph-0.0.3a1.dist-info/LICENSE
umls_graph-0.0.3a1.dist-info/METADATA
umls_graph-0.0.3a1.dist-info/WHEEL
umls_graph-0.0.3a1.dist-info/entry_points.txt
umls_graph-0.0.3a1.dist-info/top_level.txt
umls_graph-0.0.3a1.dist-info/RECORD
