Metadata-Version: 2.1
Name: umls-graph
Version: 0.0.3a1
Summary: Build medical knowledge graph based on Unified Medical Language System (UMLS)
Home-page: https://github.com/dhchenx/umls-graph
Author: Donghua Chen
Author-email: douglaschan@126.com
License: MIT
Project-URL: Bug Reports, https://github.com/dhchenx/umls-graph/issues
Keywords: unified medical language system,UMLS,knowledge graph,medical knowledge,medical concept,neo4j
Platform: UNKNOWN
Classifier: Development Status :: 3 - Alpha
Classifier: Intended Audience :: Developers
Classifier: Topic :: Software Development :: Build Tools
Classifier: License :: OSI Approved :: MIT License
Classifier: Programming Language :: Python :: 3
Classifier: Programming Language :: Python :: 3.6
Classifier: Programming Language :: Python :: 3.7
Classifier: Programming Language :: Python :: 3.8
Classifier: Programming Language :: Python :: 3.9
Classifier: Programming Language :: Python :: 3 :: Only
Requires-Python: >=3.6, <4
License-File: LICENSE
Requires-Dist: pymysql
Requires-Dist: quick-csv
Requires-Dist: dask
Requires-Dist: pyqt5
Provides-Extra: dev
Requires-Dist: check-manifest ; extra == 'dev'
Provides-Extra: test
Requires-Dist: coverage ; extra == 'test'
